sbom_manager/__init__.py
sbom_manager/cli.py
sbom_manager/config.py
sbom_manager/db.py
sbom_manager/generate.py
sbom_manager/input.py
sbom_manager/log.py
sbom_manager/output.py
sbom_manager/scan.py
sbom_manager/store.py
sbom_manager/version.py
sbom_manager-0.3.1.dist-info/LICENSE
sbom_manager-0.3.1.dist-info/METADATA
sbom_manager-0.3.1.dist-info/WHEEL
sbom_manager-0.3.1.dist-info/entry_points.txt
sbom_manager-0.3.1.dist-info/top_level.txt
sbom_manager-0.3.1.dist-info/RECORD
